consul_dns_srv/__init__.py
consul_dns_srv-0.0.2.dist-info/METADATA
consul_dns_srv-0.0.2.dist-info/WHEEL
consul_dns_srv-0.0.2.dist-info/top_level.txt
consul_dns_srv-0.0.2.dist-info/RECORD
